LICENSE
MANIFEST.in
README.rst
setup.cfg
setup.py
django_reaktion_crm/__init__.py
django_reaktion_crm/admin.py
django_reaktion_crm/apps.py
django_reaktion_crm/models.py
django_reaktion_crm/tests.py
django_reaktion_crm/views.py
django_reaktion_crm.egg-info/PKG-INFO
django_reaktion_crm.egg-info/SOURCES.txt
django_reaktion_crm.egg-info/dependency_links.txt
django_reaktion_crm.egg-info/top_level.txt
django_reaktion_crm/management/.DS_Store
django_reaktion_crm/management/commands/analyze.py
django_reaktion_crm/management/commands/error_report.py
django_reaktion_crm/management/commands/import_csv.py
django_reaktion_crm/management/commands/import_simple.py
django_reaktion_crm/management/commands/import_tracking.py
django_reaktion_crm/management/commands/__pycache__/analyze.cpython-39.pyc
django_reaktion_crm/management/commands/__pycache__/import_csv.cpython-39.pyc
django_reaktion_crm/management/commands/__pycache__/import_simple.cpython-39.pyc
django_reaktion_crm/management/commands/__pycache__/import_tracking.cpython-39.pyc
django_reaktion_crm/migrations/0001_initial.py
django_reaktion_crm/migrations/0002_auto_20210412_1422.py
django_reaktion_crm/migrations/0003_clients_campaigns.py
django_reaktion_crm/migrations/0004_auto_20211014_1201.py
django_reaktion_crm/migrations/__init__.py
django_reaktion_crm/templates/admin/django_reaktion_crm/change_form.html
django_reaktion_crm/templates/admin/django_reaktion_crm/change_list.html